InterfaceCreator/__init__.py
InterfaceCreator/cli.py
interface_creator-1.0.1.dist-info/LICENSE
interface_creator-1.0.1.dist-info/METADATA
interface_creator-1.0.1.dist-info/WHEEL
interface_creator-1.0.1.dist-info/entry_points.txt
interface_creator-1.0.1.dist-info/top_level.txt
interface_creator-1.0.1.dist-info/RECORD
