Metadata-Version: 2.1
Name: interface-creator
Version: 1.0.1
Summary: Creates interfaces from python files
Author: Zackary W
Classifier: Programming Language :: Python :: 3
Classifier: Programming Language :: Python :: 3.7
Classifier: Programming Language :: Python :: 3.8
Classifier: Programming Language :: Python :: 3.9
License-File: LICENSE
Requires-Dist: click
